sksurgeryeval/__init__.py
sksurgeryeval/__main__.py
sksurgeryeval/_version.py
sksurgeryeval/algorithms/__init__.py
sksurgeryeval/algorithms/algorithms.py
sksurgeryeval/algorithms/background_image.py
sksurgeryeval/algorithms/locators.py
sksurgeryeval/logging/__init__.py
sksurgeryeval/logging/surgery_logger.py
sksurgeryeval/shapes/__init__.py
sksurgeryeval/shapes/cone.py
sksurgeryeval/ui/__init__.py
sksurgeryeval/ui/sksurgeryeval_command_line.py
sksurgeryeval/ui/sksurgeryeval_demo.py
sksurgeryeval/widgets/__init__.py
sksurgeryeval/widgets/overlay.py
scikit_surgery_evaluation-0.0.4.dist-info/LICENSE
scikit_surgery_evaluation-0.0.4.dist-info/METADATA
scikit_surgery_evaluation-0.0.4.dist-info/WHEEL
scikit_surgery_evaluation-0.0.4.dist-info/entry_points.txt
scikit_surgery_evaluation-0.0.4.dist-info/top_level.txt
scikit_surgery_evaluation-0.0.4.dist-info/RECORD
