Metadata-Version: 2.1
Name: scikit-surgery-evaluation
Version: 0.0.4
Summary: A python library for performing surgical skills evaluation
Home-page: https://github.com/UCL/scikit-surgery-evaluation
Author: Stephen Thompson
Author-email: YOUR-EMAIL@ucl.ac.uk
License: BSD-3 license
Keywords: medical imaging
Platform: UNKNOWN
Classifier: Development Status :: 3 - Alpha
Classifier: Intended Audience :: Developers
Classifier: Intended Audience :: Healthcare Industry
Classifier: Intended Audience :: Information Technology
Classifier: Intended Audience :: Science/Research
Classifier: License :: OSI Approved :: BSD License
Classifier: Programming Language :: Python
Classifier: Programming Language :: Python :: 2
Classifier: Programming Language :: Python :: 3
Classifier: Topic :: Scientific/Engineering :: Information Analysis
Classifier: Topic :: Scientific/Engineering :: Medical Science Apps.
Requires-Dist: numpy
Requires-Dist: ipykernel
Requires-Dist: nbsphinx
Requires-Dist: vtk
Requires-Dist: PySide2
Requires-Dist: scikit-surgeryvtk (>=0.12.3)
Requires-Dist: scikit-surgerycore
Requires-Dist: scikit-surgeryutils
Requires-Dist: scikit-surgerynditracker
Requires-Dist: scikit-surgeryarucotracker (>=0.0.4)
